PyCutee/__init__.py
PyCutee/button_rounded.py
PyCutee/button_simple.py
PyCutee-0.0.6.dist-info/METADATA
PyCutee-0.0.6.dist-info/WHEEL
PyCutee-0.0.6.dist-info/top_level.txt
PyCutee-0.0.6.dist-info/RECORD
