Metadata-Version: 2.1
Name: PyCutee
Version: 0.0.6
Summary: This app is a lil framework for PyQt5 like bootstrap for HTML5
Author: Codingrule
Author-email: <ioumih32@gmail.com>
Keywords: python,framework,pyqt5,frontend,customize,UI
Classifier: Development Status :: 1 - Planning
Classifier: Intended Audience :: Developers
Classifier: Programming Language :: Python :: 3
Classifier: Operating System :: Unix
Classifier: Operating System :: MacOS :: MacOS X
Classifier: Operating System :: Microsoft :: Windows
Requires-Dist: PyQt5
